st_multimodal_chatinput/__init__.py
st_multimodal_chatinput/frontend/build/asset-manifest.json
st_multimodal_chatinput/frontend/build/bootstrap.min.css
st_multimodal_chatinput/frontend/build/index.html
st_multimodal_chatinput/frontend/build/static/js/main.eb1aa2d6.js
st_multimodal_chatinput/frontend/build/static/js/main.eb1aa2d6.js.LICENSE.txt
st_multimodal_chatinput/frontend/build/static/js/main.eb1aa2d6.js.map
st_multimodal_chatinput-0.2.1.dist-info/LICENSE
st_multimodal_chatinput-0.2.1.dist-info/METADATA
st_multimodal_chatinput-0.2.1.dist-info/WHEEL
st_multimodal_chatinput-0.2.1.dist-info/top_level.txt
st_multimodal_chatinput-0.2.1.dist-info/RECORD
