Metadata-Version: 2.1
Name: st-multimodal-chatinput
Version: 0.2.1
Summary: Streamlit component that allows you to accept multi-modal inputs through a chat interface.
Home-page: https://github.com/het-25/st-multimodal-chatinput
Author: Het Patel
Author-email: 2522het.patel@gmail.com
Requires-Python: >=3.7
License-File: LICENSE
Requires-Dist: streamlit >=0.63
Provides-Extra: devel
Requires-Dist: wheel ; extra == 'devel'
Requires-Dist: pytest ==7.4.0 ; extra == 'devel'
Requires-Dist: playwright ==1.36.0 ; extra == 'devel'
Requires-Dist: requests ==2.31.0 ; extra == 'devel'
Requires-Dist: pytest-playwright-snapshot ==1.0 ; extra == 'devel'
Requires-Dist: pytest-rerunfailures ==12.0 ; extra == 'devel'
